binance/BinanceClient.py
binance/BinanceException.py
binance/Pair.py
binance/Timer.py
binance/__init__.py
binance/enums.py
binance/subscriptions.py
binance_aio-0.0.3.dist-info/LICENSE
binance_aio-0.0.3.dist-info/METADATA
binance_aio-0.0.3.dist-info/WHEEL
binance_aio-0.0.3.dist-info/top_level.txt
binance_aio-0.0.3.dist-info/RECORD
