Metadata-Version: 2.1
Name: binance-aio
Version: 0.0.3
Summary: Binance asynchronous python client
Home-page: https://github.com/nardew/binance-aio
Author: nardew
Author-email: binance.aio@gmail.com
License: UNKNOWN
Platform: UNKNOWN
Classifier: Development Status :: 4 - Beta
Classifier: Framework :: AsyncIO
Classifier: Intended Audience :: Developers
Classifier: Programming Language :: Python :: 3
Classifier: Programming Language :: Python :: 3.6
Classifier: Programming Language :: Python :: 3.7
Classifier: License :: OSI Approved :: MIT License
Classifier: Operating System :: OS Independent
Classifier: Topic :: Software Development :: Libraries
Classifier: Topic :: Software Development :: Libraries :: Python Modules
Classifier: Typing :: Typed
Requires-Python: >=3.6
Requires-Dist: aiohttp (==3.6.2)
Requires-Dist: websockets (==8.1)
